xchainpy2_binance/__init__.py
xchainpy2_binance/client.py
xchainpy2_binance/const.py
xchainpy2_binance/utils.py
xchainpy2_binance/sdk/__init__.py
xchainpy2_binance/sdk/constants.py
xchainpy2_binance/sdk/environment.py
xchainpy2_binance/sdk/exc.py
xchainpy2_binance/sdk/http_cli.py
xchainpy2_binance/sdk/messages.py
xchainpy2_binance/sdk/utils.py
xchainpy2_binance/sdk/wallet.py
xchainpy2_binance/sdk/proto/__init__.py
xchainpy2_binance/sdk/proto/dex_pb2.py
xchainpy2_binance/sdk/proto/dex_pb2.pyi
xchainpy2_binance/sdk/proto/dex_pb2_grpc.py
xchainpy2_binance/tests/test_keys.py
xchainpy2_binance-0.0.10.dist-info/LICENSE
xchainpy2_binance-0.0.10.dist-info/METADATA
xchainpy2_binance-0.0.10.dist-info/WHEEL
xchainpy2_binance-0.0.10.dist-info/top_level.txt
xchainpy2_binance-0.0.10.dist-info/RECORD
