Metadata-Version: 2.1
Name: xchainpy2_binance
Version: 0.0.10
Summary: XChainPy2 Binance Beacon Chain Client
Author-email: Tirinox <developer@tirinox.ru>
License: MIT
Project-URL: source, https://github.com/tirinox/xchainpy
Keywords: Crypto,Binance,BNB,Beacon,Blockchain,XChain
Classifier: Development Status :: 3 - Alpha
Classifier: Intended Audience :: Developers
Classifier: Topic :: Software Development :: Build Tools
Classifier: License :: OSI Approved :: MIT License
Classifier: Programming Language :: Python :: 3
Classifier: Programming Language :: Python :: 3.6
Classifier: Programming Language :: Python :: 3.7
Classifier: Programming Language :: Python :: 3.8
Classifier: Programming Language :: Python :: 3.9
Classifier: Programming Language :: Python :: 3.10
Classifier: Programming Language :: Python :: 3.11
Requires-Python: >=3.7
License-File: LICENSE
Requires-Dist: xchainpy2_utils
Requires-Dist: xchainpy2_crypto
Requires-Dist: xchainpy2_client
Requires-Dist: cosmpy>=0.9.1
Requires-Dist: ujson>=5.8.0
Requires-Dist: protobuf>=4.25.1
Provides-Extra: test
Requires-Dist: pytest; extra == "test"
